{"tx_hash": "6zh8nUHNHaokSFuGfN83eDYE9TYhUbEg1foUfuavQGb6", "action_id_social": "4otTquKtjTdHyFy9RaEK8RSDwX5w3H4KVCW6bkorN1ap-0-widget", "block_id": 84865710, "block_timestamp": "2023-02-09T20:51:38.416Z", "signer_id": "roshaan.near", "widget_name": "queryapi__IndexerStatus", "source_code": "//props indexer_name\nlet indexer_name = props.indexer_name;\n\nreturn (\n  <>\n    <h1>Indexer Status</h1>\n  </>\n);\n", "metadata": null, "branch": null, "widget_modules_used": null, "widget_url": "https://near.social/#/roshaan.near/widget/queryapi__IndexerStatus", "fact_widget_deployments_id": "b71681698f3eec8934b04f0f0842e556", "inserted_timestamp": "2000-01-01T00:00:00.000Z", "modified_timestamp": "2000-01-01T00:00:00.000Z", "__row_index": 31}