{"tx_hash": "BBSdAv52H5CfYerfs5JpAc6JMkJprgfE3AuqayEMZxqx", "action_id_social": "FwmJpiQWGDKyFicXkSRKmuv1E8dQd2eEDQYhx848zp3W-0-widget", "block_id": 100492728, "block_timestamp": "2023-09-06T04:05:42.127Z", "signer_id": "agwaze.near", "widget_name": "GenaDrop.SuccessModal", "source_code": "const PopupContainer = styled.div`\n    display: flex;\n    flex-direction: column;\n    width: 350px;\n    height: 300px;\n    border-radius: 16px;\n    padding-top: 30px;\n    background: #fff;\n    align-items: center;\n    img {\n        width: 70px;\n    }\n    h1 {\n        font-size: 25px;\n        margin-top: 10px;\n        font-weight: 600;\n    }\n`;\n\nconst PopupButtons = styled.div`\nmargin-top: 30px;\n    a {\n        border: 1.5jpx solid #0d6efd;\n        cursor: pointer;\n        margin-right: 10px;\n        transition: .3s ease-in-out;\n        padding: 7px;\n        border-radius: 8px;\n    }\n    a:hover {\n        opacity: .5;\n    }\n    button {\n        width: 120px\n    }\n`;\n\nreturn (\n  <PopupContainer>\n    <img src=\"https://cdn-icons-png.flaticon.com/128/5709/5709755.png\" alt=\"\" />\n    <h1>Successfully Listed</h1>\n    <PopupButtons>\n      <a target=\"_blank\" href={props.externalLink}>\n        View on Explorer\n      </a>\n      <button onClick={props.closeModal}>Close</button>\n    </PopupButtons>\n  </PopupContainer>\n);\n", "metadata": {"platform": "jutsu.ai"}, "branch": {"draft": null}, "widget_modules_used": null, "widget_url": "https://near.social/#/agwaze.near/widget/GenaDrop.SuccessModal", "fact_widget_deployments_id": "c2e499605f20fe8d799d20d460940dfa", "inserted_timestamp": "2023-09-06T05:39:22.087Z", "modified_timestamp": "2023-09-06T05:39:22.087Z", "__row_index": 2}