{"tx_hash": "Bbo9fNXQY5WnomC3PkjaSu5FKp71dmv5okpBT4MCZAbR", "action_id_social": "Baq2qeVcB5Y1Q7T5KX7Vsw4DFhiRGWBuDP6sohUE2can-0-widget", "block_id": 100451146, "block_timestamp": "2023-09-05T14:25:05.220Z", "signer_id": "77b8464a6283e39404b38a05d5ccb864b0f7a5d6732514a83f8e993938def1ff", "widget_name": "GreeterYourName", "source_code": "let greeting = \"Have a great day\";\n\nreturn (\n  <>\n    <div class=\"container border border-info p-3 text-center\">\n      <h1>Hello {props.user}</h1>\n\n      <p> {greeting} </p>\n    </div>\n  </>\n);\n", "metadata": {"platform": "jutsu.ai"}, "branch": {"draft": null}, "widget_modules_used": null, "widget_url": "https://near.social/#/77b8464a6283e39404b38a05d5ccb864b0f7a5d6732514a83f8e993938def1ff/widget/GreeterYourName", "fact_widget_deployments_id": "0b91a16ce5fbc66b2263bdecc99572b9", "inserted_timestamp": "2023-09-05T16:29:57.491Z", "modified_timestamp": "2023-09-05T16:29:57.491Z", "__row_index": 7}