{"tx_hash": "6hKLyjaaaqZcK1W6cAeGeBj9LrBhMa6htPiELKj8riqM", "action_id_social": "E3YxbB8EU1XTMvBPigCnLrbiCRhCZMXq5FS7LcGF1P84-0-widget", "block_id": 76727976, "block_timestamp": "2022-10-21T17:33:57.407Z", "signer_id": "mob.near", "widget_name": "Meme", "source_code": null, "metadata": null, "branch": null, "widget_modules_used": null, "widget_url": "https://near.social/#/mob.near/widget/Meme", "fact_widget_deployments_id": "35629ccdd4801abbd2cb54e0ed4256a1", "inserted_timestamp": "2000-01-01T00:00:00.000Z", "modified_timestamp": "2000-01-01T00:00:00.000Z", "__row_index": 10}