{"tx_hash": "3ZZNW4CPhLs62H9UqoV8dk6dgkNMK2nYDEZaG1DKn5Nm", "action_id_social": "8BL2Tk5Zr8uniWZhhtXVohczdtCgebrujzpkx9hjCnYH-0-widget", "block_id": 105972006, "block_timestamp": "2023-11-18T11:24:23.379Z", "signer_id": "beachsunandrockandroll.near", "widget_name": "card", "source_code": null, "metadata": null, "branch": {"draft": null}, "widget_modules_used": null, "widget_url": "https://near.social/#/beachsunandrockandroll.near/widget/card", "fact_widget_deployments_id": "28bfb962782b24e47ae8c547c28b695d", "inserted_timestamp": "2024-03-07T05:24:05.087Z", "modified_timestamp": "2024-03-07T05:24:05.087Z", "__row_index": 3}