{"tx_hash": "9sQ9hDk7VXyJrtr5NGTGEYzejCpK4TWc8WgN5nta4dfs", "action_id_social": "6gXoyU5ucT74QxrpQcxQ4sNiBgBx3ydZNweCEbsC479C-0-widget", "block_id": 108259447, "block_timestamp": "2023-12-18T15:16:08.167Z", "signer_id": "previewthomas.near", "widget_name": "devhub.components.atom.Alert", "source_code": "const Alert = ({ onClose, message }) =>\n  message && (\n    <div class=\"alert alert-warning alert-dismissible fade show\" role=\"alert\">\n      {message}\n      <button\n        type=\"button\"\n        class=\"btn-close\"\n        data-bs-dismiss=\"alert\"\n        aria-label=\"Close\"\n        onClick={onClose}\n      ></button>\n    </div>\n  );\n\nreturn Alert(props);\n", "metadata": null, "branch": null, "widget_modules_used": null, "widget_url": "https://near.social/#/previewthomas.near/widget/devhub.components.atom.Alert", "fact_widget_deployments_id": "002536cf3ffe5722baab579eaa2e3f91", "inserted_timestamp": "2024-03-07T05:24:05.087Z", "modified_timestamp": "2024-03-07T05:24:05.087Z", "__row_index": 4}