{"tx_hash": "5Rp9DGoikSskc6Coe5Jr9fxMCFcD6jNAxTNTMjDpVUG", "action_id_social": "Hcr5GRbPJPYCMX9PBE7moTaFqfrRgashn4mNvFWQVRYb-0-widget", "block_id": 99304593, "block_timestamp": "2023-08-21T08:01:48.902Z", "signer_id": "relayer.pagodaplatform.near", "widget_name": "walley-fork", "source_code": "", "metadata": null, "branch": null, "widget_modules_used": null, "widget_url": "https://near.social/#/relayer.pagodaplatform.near/widget/walley-fork", "fact_widget_deployments_id": "ef7152a5ccc6e72456c4631117c69272", "inserted_timestamp": "2024-03-07T05:24:05.087Z", "modified_timestamp": "2024-03-07T05:24:05.087Z", "__row_index": 0}