{"tx_hash": "Bv9STF7qrzczcTcGn3gwUwMxyW6JVVfG8XK3aAwrYgm1", "action_id_social": "BgTsTGs9T4CTeJ4GhW5ybJqVXmwPLotNHEb4h17yVMEQ-0-widget", "block_id": 108259933, "block_timestamp": "2023-12-18T15:24:52.847Z", "signer_id": "relayer.pagodaplatform.near", "widget_name": "DonationHub.components.organism.NewsLetter", "source_code": "const page = props.page;\nconst imageLink = \"https://i.postimg.cc/4dQF0gsY/Footer-Quote-1.png\";\n\nconst ImageContainer = styled.img`\n  ${page !== \"home\" && \"display: none;\"}\n\n  object-fit: fit;\n`;\n\nreturn (\n  <>\n    <ImageContainer src={imageLink} />\n  </>\n);\n", "metadata": {"fork_of": "lucus.near/widget/DonationHub.components.organism.NewsLetter@108259910"}, "branch": {"draft": null}, "widget_modules_used": null, "widget_url": "https://near.social/#/relayer.pagodaplatform.near/widget/DonationHub.components.organism.NewsLetter", "fact_widget_deployments_id": "71a7055e5898c2e67d9c535692411e7a", "inserted_timestamp": "2024-03-07T05:24:05.087Z", "modified_timestamp": "2024-03-07T05:24:05.087Z", "__row_index": 8}