{"tx_hash": "D9Czesw1NVTrNbZoFJvD7Lebpf2GEWAKqR5jabTkrFYp", "action_id_social": "9it3JVYGHSampPWoXbBz5xBAhgDRhLho23EccZe6B48j-0-widget", "block_id": 118098612, "block_timestamp": "2024-05-02T15:24:03.451Z", "signer_id": "events-committee.near", "widget_name": "devhub.page.post", "source_code": "const { id } = props;\n\nconst Container = styled.div`\n  padding: 0 3rem 3rem 3rem;\n  width: 100%;\n  max-width: 100%;\n\n  @media screen and (max-width: 768px) {\n    padding: 0 1rem 1rem 1rem;\n  }\n`;\n\nreturn (\n  <Container>\n    <Widget\n      src={\"events-committee.near/widget/devhub.entity.post.Post\"}\n      props={{\n        id,\n      }}\n    />\n  </Container>\n);\n", "metadata": null, "branch": null, "widget_modules_used": null, "widget_url": "https://near.social/#/events-committee.near/widget/devhub.page.post", "fact_widget_deployments_id": "4b46fbef489f50b53be3833a1ec5542a", "inserted_timestamp": "2024-05-02T16:41:38.192Z", "modified_timestamp": "2024-05-02T16:41:38.192Z", "__row_index": 59}