{"tx_hash": "HmaJTFyjYdhH45ifdhbKZ9pzbvRhCBw7f8hiMT6iB8ZD", "action_id_social": "J9gyAazkXUgAwx1gjwXphyVzuCHPTnN3KyyiHzxfTnMe-0-widget", "block_id": 108149476, "block_timestamp": "2023-12-17T06:44:01.234Z", "signer_id": "relayer.pagodaplatform.near", "widget_name": "CardAccount", "source_code": null, "metadata": null, "branch": {"draft": {"": "const children = props.children;\n\nconst tailwindCssUrl =\n  \"https://cdn.jsdelivr.net/npm/tailwindcss@2.2/dist/tailwind.min.css\";\n\nState.init({\n  theme: null,\n});\n\nconst tailwindCss = fetch(tailwindCssUrl).body;\n\nif (!tailwindCss) return \"Can't load CSS \ud83d\ude14.\";\n\nif (!state.theme) {\n  State.update({\n    theme: styled.div`\n    ${tailwindCss}`,\n  });\n}\n\nconst Theme = state.theme;\n\nreturn (\n  <Theme>\n    {\" \"}\n    <div class=\"w-[156px] h-48 bg-white rounded rounded-xl shadow border border-gray-200 relative p-4\">\n      <div class=\"text-zinc-800 text-sm font-semibold\">MetaMask</div>\n      <div class=\"text-zinc-500 text-xs font-normal\">0xf229...7b9A</div>\n      <div class=\"absolute bottom-4 text-zinc-800 font-semibold text-sm\">\n        $195.5\n      </div>\n    </div>\n  </Theme>\n);\n"}}, "widget_modules_used": null, "widget_url": "https://near.social/#/relayer.pagodaplatform.near/widget/CardAccount", "fact_widget_deployments_id": "502d6689156a0cd2adbe406ed1a904d4", "inserted_timestamp": "2024-03-07T05:24:05.087Z", "modified_timestamp": "2024-03-07T05:24:05.087Z", "__row_index": 0}