{"tx_hash": "HMJsE1v6XxTZQTfvmGvRevtMQmf26LKNANczCjSmS5Nd", "action_id_social": "AV4ffATBUgjdw5GcXZB7WirZ8p8EkqTEgZupvYUi5Xr8-0-widget", "block_id": 107688110, "block_timestamp": "2023-12-11T15:27:11.214Z", "signer_id": "7fb71a85c00216db5eac6afa2c379981234a159a83a61cee7c4b3ebc83deac76", "widget_name": "Navbar", "source_code": "return (\n  <div>\n    <div class=\"navbar navbar-expand-lg navbar-light bg-light\">\n      <div class=\"container-fluid\">\n        <a class=\"navbar-brand\" href=\"#\">\n          Navbar test\n        </a>\n        <button\n          class=\"navbar-toggler\"\n          type=\"button\"\n          data-bs-toggle=\"collapse\"\n          data-bs-target=\"#navbarSupportedContent\"\n          aria-controls=\"navbarSupportedContent\"\n          aria-expanded=\"false\"\n          aria-label=\"Toggle navigation\"\n        >\n          <span class=\"navbar-toggler-icon\"></span>\n        </button>\n        <div class=\"collapse navbar-collapse\" id=\"navbarSupportedContent\">\n          <ul class=\"navbar-nav me-auto mb-2 mb-lg-0\">\n            <li class=\"nav-item\">\n              <a class=\"nav-link active\" aria-current=\"page\" href=\"#\">\n                Explore\n              </a>\n            </li>\n            <li class=\"nav-item\">\n              <a class=\"nav-link\" href=\"#\">\n                My Collection\n              </a>\n            </li>\n            <li class=\"nav-item dropdown\">\n              <a\n                class=\"nav-link dropdown-toggle\"\n                href=\"#\"\n                id=\"navbarDropdown\"\n                role=\"button\"\n                data-bs-toggle=\"dropdown\"\n                aria-expanded=\"false\"\n              >\n                Profile\n              </a>\n              <ul class=\"dropdown-menu\" aria-labelledby=\"navbarDropdown\">\n                <li>\n                  <Web3Connect\n                    className=\"LidoStakeFormSubmitContainer\"\n                    connectLabel=\"Connect your wallet\"\n                  />\n                </li>\n                <li>\n                  <a class=\"dropdown-item\" href=\"#\">\n                    Another action\n                  </a>\n                </li>\n              </ul>\n            </li>\n          </ul>\n          <div class=\"d-flex\">\n            <input\n              class=\"form-control me-2\"\n              type=\"search\"\n              placeholder=\"Search\"\n              aria-label=\"Search\"\n            />\n            <button class=\"btn btn-outline-success\" type=\"submit\">\n              Search\n            </button>\n          </div>\n        </div>\n      </div>\n    </div>\n  </div>\n);\n", "metadata": null, "branch": null, "widget_modules_used": null, "widget_url": "https://near.social/#/7fb71a85c00216db5eac6afa2c379981234a159a83a61cee7c4b3ebc83deac76/widget/Navbar", "fact_widget_deployments_id": "26d024aaaff5488b7e0434fcec161f66", "inserted_timestamp": "2024-03-07T05:24:05.087Z", "modified_timestamp": "2024-03-07T05:24:05.087Z", "__row_index": 12}