{"tx_hash": "816Pb6bDorzgMWdufAonjpPexwHbBirZ8W1YTWB7SsvW", "action_id_social": "4gaaU7bPUXYExJiC9jcaNmbM2nBA2YP81VzbLi5tLs5N-0-widget", "block_id": 101496138, "block_timestamp": "2023-09-19T19:24:27.599Z", "signer_id": "mob.near", "widget_name": "Notification.Item.Repost", "source_code": "const { accountId, value } = props;\n\nconst overlayStyle = {\n  maxWidth: \"30em\",\n  zIndex: 1070,\n  maxHeight: \"24em\",\n  overflow: \"hidden\",\n};\n\nconst { content, popup } =\n  value.item.path === `${context.accountId}/post/main`\n    ? {\n        content: (\n          <a\n            className=\"fw-bold text-muted\"\n            href={`/mob.near/widget/MainPage.N.Post.Page?accountId=${context.accountId}&blockHeight=${value.item.blockHeight}`}\n          >\n            post\n          </a>\n        ),\n        popup: (\n          <Widget\n            src=\"mob.near/widget/MainPage.N.Post\"\n            props={{\n              accountId: context.accountId,\n              blockHeight: value.item.blockHeight,\n              hideComments: true,\n            }}\n          />\n        ),\n      }\n    : { content: \"item???\" };\n\nreturn (\n  <Widget\n    loading={props.loading}\n    src=\"mob.near/widget/Notification.Item.LR\"\n    props={{\n      L: (\n        <>\n          reposted your\n          <Widget\n            loading={content}\n            src=\"mob.near/widget/N.Common.OverlayTrigger\"\n            props={{\n              overlayStyle,\n              popup,\n              children: content,\n            }}\n          />\n        </>\n      ),\n      R:\n        value.item.path === `${context.accountId}/post/main` ? (\n          <a\n            className=\"btn btn-outline-dark rounded-5\"\n            href={`/mob.near/widget/MainPage.N.Post.Page?accountId=${context.accountId}&blockHeight=${value.item.blockHeight}`}\n          >\n            View post\n          </a>\n        ) : (\n          \"\"\n        ),\n      ...props,\n    }}\n  />\n);\n", "metadata": null, "branch": null, "widget_modules_used": null, "widget_url": "https://near.social/#/mob.near/widget/Notification.Item.Repost", "fact_widget_deployments_id": "5d90abf57342e447aba15a730ac5a022", "inserted_timestamp": "2024-03-07T05:24:05.087Z", "modified_timestamp": "2024-03-07T05:24:05.087Z", "__row_index": 1}