{"tx_hash": "34EwZqpZP3azGQLoLsEjV7tFPpHnfncNAd21amMLB3fR", "action_id_social": "CDeKmdjLccoP4FprAZENe87dYFYPKtzmAjrCozwcqU8N-0-widget", "block_id": 85156698, "block_timestamp": "2023-02-13T17:52:14.907Z", "signer_id": "events_v2.near", "widget_name": "app__frame", "source_code": "", "metadata": null, "branch": null, "widget_modules_used": null, "widget_url": "https://near.social/#/events_v2.near/widget/app__frame", "fact_widget_deployments_id": "0c4fd2949e72c2e92c10651a8bf69ff0", "inserted_timestamp": "2000-01-01T00:00:00.000Z", "modified_timestamp": "2000-01-01T00:00:00.000Z", "__row_index": 401}