{"tx_hash": "BsJKCCktPBR4EWUm7Aun6N9WQGsH8rP4XUnUDw3PusjM", "action_id_social": "B1n1Y6eeMut29seuDGD5T3VzGECKXPK2sg4vuRz8QPEV-0-widget", "block_id": 93914940, "block_timestamp": "2023-06-10T20:59:07.685Z", "signer_id": "relayer.pagodaplatform.near", "widget_name": "AwesomeAlgoChat", "source_code": null, "metadata": null, "branch": {"draft": {"": "var src = \"https://awesomealgo.com\";\nif (props.src) {\n  src = props.src;\n}\nconst css = styled.b`\nhtml {overflow: auto;}    \nhtml,\nbody,\ndiv,\niframe {\n    margin: 0px;\n    padding: 0px;\n    height: 100%;\n    min-height: 5000px;\n    border: none;\n}\niframe {\n    display: block;\n    width: 100%;\n    border: none;\n    overflow-y: auto;\n    overflow-x: hidden;\n}\n`;\n\nreturn (\n  <>\n    <css>\n      <iframe\n        src={src}\n        onMessage={(response) => window.open(response.url, \"_blank\")}\n        frameborder=\"0\"\n        marginheight=\"0\"\n        marginwidth=\"0\"\n        width=\"100%\"\n        height=\"100%\"\n        scrolling=\"auto\"\n      ></iframe>\n    </css>\n  </>\n);\n"}}, "widget_modules_used": null, "widget_url": "https://near.social/#/relayer.pagodaplatform.near/widget/AwesomeAlgoChat", "fact_widget_deployments_id": "e4cfeb0b6f670d46d171ff605ab35a95", "inserted_timestamp": "2024-03-07T05:24:05.087Z", "modified_timestamp": "2024-03-07T05:24:05.087Z", "__row_index": 5}