{"tx_hash": "3MvxAPD3CXjKL6M5d1fETM3keK4M9hnnKBzVZAWqzhz2", "action_id_social": "EcaP6R9hXqaBsJPRQvi6cruEGWpYpnMVQSAMSckcT9gA-0-widget", "block_id": 103082128, "block_timestamp": "2023-10-10T22:25:28.207Z", "signer_id": "yairnava.near", "widget_name": "Greetings", "source_code": "let greeting = \"Have a great day\";\nconst { name } = props;\n\nreturn (\n  <>\n    <div class=\"container border border-info p-3 text-center\">\n      <h1>Hello {name}</h1>\n      <h2>{props.lastname}</h2>\n      <p> {greeting} </p>\n    </div>\n  </>\n);\n", "metadata": {"name": "Greetings"}, "branch": null, "widget_modules_used": null, "widget_url": "https://near.social/#/yairnava.near/widget/Greetings", "fact_widget_deployments_id": "d98d882ead4ea9b86487805e5b347709", "inserted_timestamp": "2024-03-07T05:24:05.087Z", "modified_timestamp": "2024-03-07T05:24:05.087Z", "__row_index": 0}