{"tx_hash": "CxPYJtLVqwREZtTWw9hHt4uWK6uauPD7GEKYcep3mKYm", "action_id_social": "637PPAz8sAGtXb23pg9sztUX8K8nKuRDdDDM1NhSMecE-0-widget", "block_id": 120365321, "block_timestamp": "2024-06-03T18:34:22.981Z", "signer_id": "infrastructure-committee.near", "widget_name": "near-prpsls-bos.components.pages.about", "source_code": "/*\nLicense: MIT\nAuthor: devhub.near\nHomepage: https://github.com/NEAR-DevHub/near-prpsls-bos#readme\n*/\nreturn \"About\";\n", "metadata": null, "branch": null, "widget_modules_used": null, "widget_url": "https://near.social/#/infrastructure-committee.near/widget/near-prpsls-bos.components.pages.about", "fact_widget_deployments_id": "78068ba1a96a46de9e8f70466eeb192b", "inserted_timestamp": "2024-06-03T19:41:22.474Z", "modified_timestamp": "2024-06-03T20:42:29.468Z", "__row_index": 0}