{"tx_hash": "HXMzcWsPpx76HRfzpzya2ochjThxGPDAmseeVmNScqyT", "action_id_social": "CTeaWgehb69j6HhAYL9dJaJyJFExHX6VCXQyULyL38Dk-0-widget", "block_id": 115741750, "block_timestamp": "2024-03-29T21:07:37.739Z", "signer_id": "agiguild.near", "widget_name": "Schema.ModelName", "source_code": "\nconst humanize = (str) => {\n    if (!str) return \"\";\n    return str.replace(/([A-Z])/g, \" $1\").replace(/^./, (s) => s.toUpperCase());\n};\n\nconst genSchema = (namespace, entityType, entityTitle) => {\n    const title = entityTitle || humanize(entityType);\n    return {\n        namespace: namespace,\n        entityType: entityType,\n        entityTitle: title,\n        id: {\n            type: \"integer\",\n            displayType: \"hidden\",\n        },\n        accountId: {\n            type: \"text\",\n            displayType: \"hidden\",\n        },\n        name: {\n            type: \"string\",\n            inputProps: {\n                min: 2,\n                max: 80,\n                allowCommaAndSpace: false,\n                placeholder: `Choose a unique identifier for your ${title}.`,\n                required: true,\n            },\n            label: \"Name\",\n            order: 1,\n        },\n        displayName: {\n            type: \"string\",\n            inputProps: {\n                min: 2,\n                max: 255,\n                placeholder: \"The name that will be displayed to users.\",\n                required: true,\n            },\n            label: \"Display Name\",\n            order: 2,\n        },\n        logoUrl: {\n            type: \"string\",\n            inputProps: {\n                min: 4,\n                max: 255,\n                placeholder: `The logo URL for the ${title}.`,\n                required: false,\n            },\n\n            label: \"Logo URL\",\n            order: 5,\n        },\n        proprietary: {\n            type: \"string\",\n            inputProps: {\n                min: 4,\n                max: 255,\n                placeholder: `Whether this is a proprietary model or open source`,\n                required: false,\n            },\n            label: \"Is proprietary\",\n            order: 6,\n        }\n    }\n};\n\nreturn {genSchema};", "metadata": null, "branch": null, "widget_modules_used": null, "widget_url": "https://near.social/#/agiguild.near/widget/Schema.ModelName", "fact_widget_deployments_id": "c8ea8509914e9cf434e2b4ed982ffafa", "inserted_timestamp": "2024-03-29T22:34:44.557Z", "modified_timestamp": "2024-03-29T22:34:44.557Z", "__row_index": 4}