{"tx_hash": "Hi5zgM1ahiSQ7yUvJPxtipQ8MgTcteRuF7WP8Ksy9iBK", "action_id_social": "7MppnWeW6scYYoSZrkPW3FXVzvSezHTpj586mSFtSNkZ-0-widget", "block_id": 118099456, "block_timestamp": "2024-05-02T15:40:14.611Z", "signer_id": "events-committee.near", "widget_name": "devhub.notification.LR", "source_code": "let { accountId, blockHeight, value } = props;\n\nconst showAuthorProfile =\n  value.type == \"devhub/mention\" || value.type == \"devhub/edit\";\n\nif (showAuthorProfile) {\n  accountId = value.notifier;\n}\n\nreturn (\n  <div className=\"d-flex justify-content-between\">\n    <div className=\"me-2 text-truncate\">\n      <div className=\"text-truncate\">\n        <Widget\n          src=\"mob.near/widget/N.ProfileLine\"\n          props={{ accountId, tooltip: true, link: true }}\n        />\n      </div>\n      <div className=\"text-truncate text-muted\" style={{ paddingLeft: \"1em\" }}>\n        {props.L}\n        <Widget src=\"mob.near/widget/TimeAgo\" props={{ blockHeight }} />\n      </div>\n    </div>\n    <div className=\"text-nowrap\">{props.R}</div>\n  </div>\n);\n", "metadata": null, "branch": null, "widget_modules_used": null, "widget_url": "https://near.social/#/events-committee.near/widget/devhub.notification.LR", "fact_widget_deployments_id": "6d7e49a8a7dbc5033ca5e924a7e6b56b", "inserted_timestamp": "2024-05-02T17:39:26.862Z", "modified_timestamp": "2024-05-02T17:39:26.862Z", "__row_index": 5}