{"tx_hash": "EK6xPt9RmEMUSnsF6WEai99xnjvsX3XbhdwwYFzg8YkW", "action_id_social": "9P1tNgqFYg4cz1Ru4QtYSCUFKN4NSGMdHM4FtZRidCTu-0-widget", "block_id": 112437282, "block_timestamp": "2024-02-09T04:17:08.588Z", "signer_id": "james.near", "widget_name": "Badge", "source_code": "const image = props.image;\n\nconst accountId = props.accountId ?? context.accountId;\nif (!accountId) {\n  return \"\";\n}\n\nconst color =\n  props.color || Social.get(`${accountId}/badge/builder/${accountId}`);\n\nlet isBuilder = props.isBuilder ?? false;\n\nconst badgeData =\n  props.badgeData ||\n  Social.get(`${context.accountId}/badge/builder/${accountId}`) ||\n  Social.get(`${accountId}/badge/builder/${accountId}`);\n\nif (badgeData.length > 0 || badgeData === \"\") {\n  isBuilder = true;\n}\n\nreturn (\n  <>\n    {isBuilder && image && (\n      <Widget src=\"mob.near/widget/Image\" props={{ image }} />\n    )}\n  </>\n);\n", "metadata": {"fork_of": "mob.near/widget/ProfileEditor@94189914"}, "branch": null, "widget_modules_used": null, "widget_url": "https://near.social/#/james.near/widget/Badge", "fact_widget_deployments_id": "6ae96ea3688e3d02428e6b35e140868f", "inserted_timestamp": "2024-03-07T05:24:05.087Z", "modified_timestamp": "2024-03-07T05:24:05.087Z", "__row_index": 0}