{"tx_hash": "LvV44xE693caz16V7D51KsyEgLEpYGJwvpkmb975Q9X", "action_id_social": "EdYnD7vmc8BFihryPBb1xi5CBNEjnPdV1n1EWnQveAxx-0-widget", "block_id": 103003804, "block_timestamp": "2023-10-09T20:59:28.280Z", "signer_id": "chess-game.near", "widget_name": "ChessGameTab.AI", "source_code": "const contractId = \"app.chess-game.near\";\nconst buttonWidget = \"chess-game.near/widget/ChessGameButton\";\n\nState.init({\n  difficulty: \"Easy\",\n});\n\nconst selectDifficulty = (event) => {\n  State.update({\n    difficulty: event.target.value,\n  });\n};\nconst createAiGame = () => {\n  Near.call(contractId, \"create_ai_game\", {\n    difficulty: state.difficulty,\n  });\n};\n\nconst GameCreator = styled.div`\n  margin-top: 2rem;\n  display: flex;\n  flex-direction: column;\n  align-items: flex-start;\n\n  > *:not(h2) {\n    margin: 0.2rem 0;\n  }\n\n  h2, h3, h4 {\n    align-self: center;\n  }\n`;\n\nreturn (\n  <GameCreator>\n    <h2>Create New AI Game:</h2>\n    <span>Difficulty:</span>\n    <select onChange={selectDifficulty} value={state.difficulty}>\n      <option value=\"Easy\">Easy</option>\n      <option value=\"Medium\">Medium</option>\n      <option value=\"Hard\">Hard</option>\n    </select>\n    <span>\n      <i>Higher difficulties consume more gas!</i>\n    </span>\n    <Widget\n      src={buttonWidget}\n      props={{\n        onClick: createAiGame,\n        fontSize: \"1.4rem\",\n        content: \"Create\",\n      }}\n    />\n  </GameCreator>\n);\n", "metadata": null, "branch": null, "widget_modules_used": null, "widget_url": "https://near.social/#/chess-game.near/widget/ChessGameTab.AI", "fact_widget_deployments_id": "df00e7521a2745a5e840bc631e4094c7", "inserted_timestamp": "2024-03-07T05:24:05.087Z", "modified_timestamp": "2024-03-07T05:24:05.087Z", "__row_index": 0}