{"tx_hash": "DbrtJDy9LRoX6y3fUA9vah2Cp2ScEN4SPV87McoYZ6Yr", "action_id_social": "9iiK7xqAUop5LpLuwVQVy8Dm6RKL1pjx3qkKtvbYowet-0-widget", "block_id": 115914300, "block_timestamp": "2024-04-01T11:16:50.055Z", "signer_id": "abdullahi3000.near", "widget_name": "harmonic.pitch", "source_code": "const code = `\n  <!DOCTYPE html>\n  <html lang=\"en\">\n    <head>\n      <style>\n        body {\n          display: flex;\n          justify-content: center;\n          align-items: center;\n          height: 100vh;\n          background-color: #f0f0f0;\n        }\n        iframe {\n          /* Adjust iframe size as needed */\n          width: 80%;\n          height: 450px; /* Adjust height based on the aspect ratio */\n        }\n      </style>\n    </head>\n    <body>\n\n      <iframe src=\"https://harmonicguild-my.sharepoint.com/personal/quinn_harmonicguild_io/_layouts/15/stream.aspx?id=%2Fpersonal%2Fquinn%5Fharmonicguild%5Fio%2FDocuments%2FContent%2FAttachments%2FProduct%20Demo%5FShort%5FNoMusic%201%2Emp4&ga=1&referrer=StreamWebApp%2EWeb&referrerScenario=AddressBarCopied%2Eview\" title=\"Harmonic Guild Pitch\" frameborder=\"0\" allow=\"accelerometer; autoplay; clipboard-write; encrypted-media; gyroscope; picture-in-picture\" allowfullscreen></iframe>\n\n    </body>\n  </html>\n`;\n\nreturn (\n  <div\n    className=\"w-100\"\n    style={{\n      minHeight: \"500px\",\n      minWidth: \"300px\",\n    }}\n  >\n    <iframe\n      iframeResizer\n      className=\"w-100\"\n      srcDoc={code}\n      message={{\n        data: chartData,\n        colors,\n        balances: {\n          totalUsd: balances.totalUsd,\n          balancesTotal: balancesTotal,\n        },\n      }}\n    />\n  </div>\n);\n", "metadata": {"fork_of": "abdullahi3000.near/widget/config.feed@115890448"}, "branch": null, "widget_modules_used": null, "widget_url": "https://near.social/#/abdullahi3000.near/widget/harmonic.pitch", "fact_widget_deployments_id": "03524bab64017e475fe21ff9fadf3b27", "inserted_timestamp": "2024-04-01T12:33:40.493Z", "modified_timestamp": "2024-04-01T12:33:40.493Z", "__row_index": 33}