{"tx_hash": "NDYdKoh7kzMSTfGYYghiaGNMg8Bynd7saviM8sfeTUa", "action_id_social": "CRbmaDAaVMofLKdHV9ipV19bXFYN6WxEuNZwpu89UHDq-0-widget", "block_id": 106738680, "block_timestamp": "2023-11-28T14:26:09.407Z", "signer_id": "inscribe.near", "widget_name": "lib.TableStyle", "source_code": "const TableOuter = styled.div``;\nconst TableContainer = styled.div`\n  height: 320px;\n  overflow: hidden;\n`;\n\nconst IndexTableBody = styled.tbody``;\n\nconst IndexTable = styled.table`\n  border-spacing: 10px;\n  width: 100%;\n`;\n\nconst IndexHeaderTr = styled.tr`\n  width: 100%;\n  top: 20px;\n  left: 0;\n`;\n\nconst IndexTd = styled.td`\n  font-size: 14px;\n  color: #fffffff0;\n  max-width: 160px;\n  @media (min-width: 640px) {\n    max-width: auto;\n  }\n`;\n\nconst IndexTh = styled.th`\n  font-size: 14px;\n  color: #ffffffa8;\n  font-weight: 600;\n`;\n\nconst IndexDataTr = styled.tr`\n  background: #18181805;\n  height: 56px;\n`;\n\nconst AddressData = styled.div`\n  overflow: hidden;\n  text-overflow: ellipsis;\n`;\n\nconst TableFooter = styled.div`\n  display: flex;\n  justify-content: space-between;\n  align-items: center;\n`;\n\nconst TableRowsAmount = styled.div`\n  font-size: 14px;\n  font-weight: 600;\n  color: #ffffff66;\n`;\n", "metadata": null, "branch": null, "widget_modules_used": null, "widget_url": "https://near.social/#/inscribe.near/widget/lib.TableStyle", "fact_widget_deployments_id": "0f4aa26e6a05282a04b89cbc5fbd7c96", "inserted_timestamp": "2024-03-07T05:24:05.087Z", "modified_timestamp": "2024-03-07T05:24:05.087Z", "__row_index": 0}