{"tx_hash": "8MG2WrGpjL4R1yQkR3dpxPsxbt3fhzc88xVWFmog9ycF", "action_id_social": "21v3Md9VnUrQ5iC53NeibejH5HJfrsNeLvjmbv68DQfR-0-widget", "block_id": 102533005, "block_timestamp": "2023-10-03T15:53:09.423Z", "signer_id": "scopalaffairs.near", "widget_name": "Recommender.Engagement.ImageTracked", "source_code": "const handleClick = () => {\n  State.update({ clicked: true });\n};\n\nState.init({\n  clicked: false,\n});\n\nreturn (\n  <div onClick={handleClick}>\n    <Widget\n      src=\"near/widget/Recommender.Service.EngagementTracker\"\n      props={{\n        accountId: props.accountId,\n        accountIdRank: props.accountIdRank,\n        fromContext: props.fromContext,\n        event: \"Profile Interest | Clicked on Avatar Image\",\n        onClick: state.clicked,\n      }}\n    />\n      <Widget\n        src=\"mob.near/widget/Image\"\n        props={{\n          image: props.profileImage,\n          alt: props.profileImageAlt,\n          fallbackUrl:\n            \"https://ipfs.near.social/ipfs/bafkreibiyqabm3kl24gcb2oegb7pmwdi6wwrpui62iwb44l7uomnn3lhbi\",\n        }}\n      />\n  </div>\n);", "metadata": null, "branch": null, "widget_modules_used": null, "widget_url": "https://near.social/#/scopalaffairs.near/widget/Recommender.Engagement.ImageTracked", "fact_widget_deployments_id": "d0ed1c28969c3948a58ecb4a6b4584a7", "inserted_timestamp": "2024-03-07T05:24:05.087Z", "modified_timestamp": "2024-03-07T05:24:05.087Z", "__row_index": 1}